runoncluster/__init__.py
runoncluster/cli.py
runoncluster-1.0.2.dist-info/DESCRIPTION.rst
runoncluster-1.0.2.dist-info/METADATA
runoncluster-1.0.2.dist-info/RECORD
runoncluster-1.0.2.dist-info/WHEEL
runoncluster-1.0.2.dist-info/entry_points.txt
runoncluster-1.0.2.dist-info/metadata.json
runoncluster-1.0.2.dist-info/top_level.txt
