Metadata-Version: 2.0
Name: runoncluster
Version: 1.0.2
Summary: CLI tools for interaction with tl-app
Home-page: https://github.com/BerkeleyBiostats/runoncluster/
Author: Marc Paré
Author-email: marc@rvit.co
License: MIT
Platform: UNKNOWN
Requires-Dist: requests
Requires-Dist: click
